huaweicloudsdkvss/__init__.py
huaweicloudsdkvss/v3/__init__.py
huaweicloudsdkvss/v3/vss_async_client.py
huaweicloudsdkvss/v3/vss_client.py
huaweicloudsdkvss/v3/model/__init__.py
huaweicloudsdkvss/v3/model/authorize_domains_request.py
huaweicloudsdkvss/v3/model/authorize_domains_request_body.py
huaweicloudsdkvss/v3/model/authorize_domains_response.py
huaweicloudsdkvss/v3/model/business_risk_item.py
huaweicloudsdkvss/v3/model/cancel_tasks_request.py
huaweicloudsdkvss/v3/model/cancel_tasks_request_body.py
huaweicloudsdkvss/v3/model/cancel_tasks_response.py
huaweicloudsdkvss/v3/model/create_domains_request.py
huaweicloudsdkvss/v3/model/create_domains_request_body.py
huaweicloudsdkvss/v3/model/create_domains_response.py
huaweicloudsdkvss/v3/model/create_tasks_request.py
huaweicloudsdkvss/v3/model/create_tasks_request_body.py
huaweicloudsdkvss/v3/model/create_tasks_response.py
huaweicloudsdkvss/v3/model/delete_domains_request.py
huaweicloudsdkvss/v3/model/delete_domains_response.py
huaweicloudsdkvss/v3/model/domain_item.py
huaweicloudsdkvss/v3/model/domain_settings.py
huaweicloudsdkvss/v3/model/download_task_report_request.py
huaweicloudsdkvss/v3/model/download_task_report_response.py
huaweicloudsdkvss/v3/model/execute_generate_report_request.py
huaweicloudsdkvss/v3/model/execute_generate_report_request_body.py
huaweicloudsdkvss/v3/model/execute_generate_report_response.py
huaweicloudsdkvss/v3/model/list_business_risks_request.py
huaweicloudsdkvss/v3/model/list_business_risks_response.py
huaweicloudsdkvss/v3/model/list_domains_request.py
huaweicloudsdkvss/v3/model/list_domains_response.py
huaweicloudsdkvss/v3/model/list_port_results_request.py
huaweicloudsdkvss/v3/model/list_port_results_response.py
huaweicloudsdkvss/v3/model/list_task_histories_request.py
huaweicloudsdkvss/v3/model/list_task_histories_response.py
huaweicloudsdkvss/v3/model/operate_info_response_body.py
huaweicloudsdkvss/v3/model/port_item.py
huaweicloudsdkvss/v3/model/show_domain_settings_request.py
huaweicloudsdkvss-3.1.58.dist-info/LICENSE
huaweicloudsdkvss-3.1.58.dist-info/METADATA
huaweicloudsdkvss-3.1.58.dist-info/WHEEL
huaweicloudsdkvss-3.1.58.dist-info/top_level.txt
huaweicloudsdkvss-3.1.58.dist-info/RECORD
